{
  "title_mr": "गजाननाच्या भजनात नाहतो",
  "title_en": "Gajananachya Bhajanat Nahato",
  "bhajan_mr": "शेगावीच्या राणाला डोळे भरून पाहातो ।\nआम्ही गजाननाच्या भजनात नहातो ।।धृ।।\n\nदत्तरूपी गजानन, सत्यरूपी गजानन ।\nदेवरूपी गजानन, तुम्हा आम्हा पावो ।\nआम्ही गजाननाच्या भजनात नहातो ।।१।।\n\nप्रेमरूपी गजानन, देहरूपी गजानन ।\nसखारूपी गजानन, तुम्हा आम्हा लाभो ।\nआम्ही गजाननाच्या भजनात नहातो ।।२।।\n\nसांई रूपी गजानन, सूर्यरूपी गजानन ।\nआत्मारूपी गजानन, अंतरंगी राहो ।\nआम्ही गजाननाच्या भजनात नहातो ।।३।।\n\nमातृरूपी गजानन, पितृरूपी गजानन ।\nगुरूरूपी गजानन, आम्हा सुख देवो ।\nआम्ही गजाननाच्या भजनात नहातो ।।४।।",
  "bhajan_en": "Shegavichya ranala dole bharun pahato |\nAmhi Gajananachya bhajanat nahato ||Dhru||\n\nDattarupi Gajanan, Satyarupi Gajanan |\nDevarupi Gajanan, tumha amha pavo |\nAmhi Gajananachya bhajanat nahato ||1||\n\nPremarupi Gajanan, Deharupi Gajanan |\nSakharupi Gajanan, tumha amha labho |\nAmhi Gajananachya bhajanat nahato ||2||\n\nSai rupi Gajanan, Suryarupi Gajanan |\nAtmarupi Gajanan, antarangi raho |\nAmhi Gajananachya bhajanat nahato ||3||\n\nMatrurupi Gajanan, Pitrurupi Gajanan |\nGururupi Gajanan, amha sukh devo |\nAmhi Gajananachya bhajanat nahato ||4||",
  "youtube_video_id": "M0HQiZi36uk",
  "image": "gajananachya_bhajanat_nahato.png"
}